plotlyink/__init__.py
plotlyink/cli.py
plotlyink/colors.py
plotlyink/config.py
plotlyink/core.py
plotlyink/register_pandas_accessors.py
plotlyink/utils.py
plotlyink-0.0.1.dev12.dist-info/METADATA
plotlyink-0.0.1.dev12.dist-info/RECORD
plotlyink-0.0.1.dev12.dist-info/WHEEL
plotlyink-0.0.1.dev12.dist-info/entry_points.txt
plotlyink-0.0.1.dev12.dist-info/pbr.json
plotlyink-0.0.1.dev12.dist-info/top_level.txt
