Metadata-Version: 2.1
Name: plotlyink
Version: 0.0.1.dev12
Summary: Productivity Tools for Plotly + Pandas
Home-page: https://github.com/gjeusel/plotlyink
Author: See AUTHORS
Author-email: jeusel.guillaume@gmail.com
License: UNKNOWN
Platform: UNKNOWN
Classifier: Development Status :: 4 - Beta
Classifier: Operating System :: MacOS :: MacOS X
Classifier: Operating System :: Microsoft :: Windows
Classifier: Operating System :: POSIX
Classifier: License :: OSI Approved :: MIT License
Classifier: Programming Language :: Python
Classifier: Programming Language :: Python :: 3.6
Requires-Dist: pandas (>=0.23.0)
Requires-Dist: numpy
Requires-Dist: plotly
Requires-Dist: colorlover
